MANIFEST.in
README.rst
requirements.txt
setup.cfg
setup.py
tests-requirements.txt
CloudSearch_Logger.egg-info/PKG-INFO
CloudSearch_Logger.egg-info/SOURCES.txt
CloudSearch_Logger.egg-info/dependency_links.txt
CloudSearch_Logger.egg-info/not-zip-safe
CloudSearch_Logger.egg-info/requires.txt
CloudSearch_Logger.egg-info/top_level.txt
cloudsearch_logger/__init__.py
cloudsearch_logger/constants.py
cloudsearch_logger/exceptions.py
cloudsearch_logger/formatter.py
cloudsearch_logger/handler.py