Metadata-Version: 1.1
Name: CloudSearch-Logger
Version: 0.2
Summary: Python Logger for Logging Data on Amazon CloudSearch
Home-page: https://github.com/ahmadjavedse/cloudsearch-logger.git
Author: Ahmad Javed
Author-email: ahmadjaved.se@gmail.com
License: UNKNOWN
Keywords: python cloudsearch logger cloudsearch-logger amazon cloudsearch logging
Platform: UNKNOWN
Classifier: Development Status :: 3 - Alpha
Classifier: Intended Audience :: Developers
Classifier: Topic :: Software Development :: Build Tools
Classifier: Topic :: Software Development :: Libraries :: Python Modules
Classifier: Programming Language :: Python :: 2.7
